wg_confgen/__init__.py
wg_confgen/wg_confgen.py
wg_confgen-0.3.0.dist-info/METADATA
wg_confgen-0.3.0.dist-info/WHEEL
wg_confgen-0.3.0.dist-info/entry_points.txt
wg_confgen-0.3.0.dist-info/RECORD
