Metadata-Version: 2.4
Name: wg-confgen
Version: 0.3.0
Summary: Generator of consistent Wireguard configurations
Requires-Python: >=3.11
